[
  {
    "text": "GoLang学习笔记",
    "items": [
      { "text": "开发环境搭建", "link": "/GoLang/001-environment" },
      {
        "text": "GO的常见使用场景",
        "link": "/GoLang/002-chang_jin"
      }
    ]
  },
  {
    "text": "ES学习笔记",
    "items": [
      {
        "text": "Let和Const",
        "link": "/ES/001-variable"
      },
      {
        "text": "字符串",
        "link": "/ES/002-string"
      },
      {
        "text": "数组",
        "link": "/ES/003-array"
      },
      {
        "text": "对象的扩展",
        "link": "/ES/004-object"
      },
      {
        "text": "函数的扩展",
        "link": "/ES/005-function"
      },
      {
        "text": "解构赋值",
        "link": "/ES/006-destructuring"
      },
      {
        "text": "运算符",
        "link": "/ES/007-operator"
      },
      {
        "text": "数据类型",
        "link": "/ES/008-type"
      }
    ]
  },
  {
    "text": "Linux学习笔记",
    "items": [{ "text": "常用命令", "link": "/Linux/001-command" }]
  },
  {
    "text": "Docker学习笔记",
    "items": [
      {
        "text": "安装",
        "link": "/Docker/001-install"
      },
      {
        "text": "搭建mysql数据库",
        "link": "/Docker/002-use"
      }
    ]
  }
]
